Metadata-Version: 1.1
Name: couzinswarm
Version: 0.0.2
Summary: Simulating fish swarming behavior with the model by Iain Couzin et al.
Home-page: https://www.github.com/benmaier/couzinswarm
Author: Benjamin F. Maier
Author-email: bfmaier@physik.hu-berlin.de
License: MIT
Platform: UNKNOWN
Classifier: Programming Language :: Python :: 3
